arinfopy/__init__.py
arinfopy/adsobinapi.py
arinfopy/cli/__init__.py
arinfopy/cli/arinfopy.py
arinfopy-3.2.2.dist-info/LICENSE
arinfopy-3.2.2.dist-info/METADATA
arinfopy-3.2.2.dist-info/WHEEL
arinfopy-3.2.2.dist-info/entry_points.txt
arinfopy-3.2.2.dist-info/top_level.txt
arinfopy-3.2.2.dist-info/RECORD
