Metadata-Version: 2.1
Name: arinfopy
Version: 3.2.2
Summary: A package to read and write ADSO/BIN data files.
Home-page: https://github.com/Simularia/arinfopy
Author: Giuseppe Carlino
Author-email: g.carlino@simularia.it
License: GNU GPLv2
Classifier: Programming Language :: Python :: 3.9
Classifier: License :: OSI Approved :: GNU General Public License v2 (GPLv2)
Classifier: Operating System :: OS Independent
Requires-Python: >=3.9
License-File: LICENSE
Requires-Dist: numpy>=1.24
Requires-Dist: setuptools>=70.0.0
